zebe/utils/__init__.py
zebe/utils/ai_util.py
zebe/utils/datetime_util.py
zebe/utils/email_util.py
zebe/utils/entity_util.py
zebe/utils/file_util.py
zebe/utils/process_util.py
zebe/utils/sqlite_util.py
zebe_python_utils-0.0.8.dist-info/LICENSE.txt
zebe_python_utils-0.0.8.dist-info/METADATA
zebe_python_utils-0.0.8.dist-info/RECORD
zebe_python_utils-0.0.8.dist-info/WHEEL
zebe_python_utils-0.0.8.dist-info/top_level.txt
