Metadata-Version: 2.1
Name: zebe-python-utils
Version: 0.0.8
Summary: zebe-python-utils
Home-page: https://gitee.com/zebe/zebe-python-utils
Author: Zebe
Author-email: zebe@vip.qq.com
License: UNKNOWN
